multigit_gx/mgitcmd.py
multigit_gx/multigit.py
multigit_gx/src/__init__.py
multigit_gx/src/mg_actions.py
multigit_gx/src/mg_auth_failure_mgr.py
multigit_gx/src/mg_button_history.py
multigit_gx/src/mg_config.py
multigit_gx/src/mg_const.py
multigit_gx/src/mg_dialog_about.py
multigit_gx/src/mg_dialog_apply_mgit_file.py
multigit_gx/src/mg_dialog_clone_from_mgit.py
multigit_gx/src/mg_dialog_export_csv.py
multigit_gx/src/mg_dialog_export_mgit.py
multigit_gx/src/mg_dialog_full_licence_info.py
multigit_gx/src/mg_dialog_git_commit.py
multigit_gx/src/mg_dialog_git_create_branch.py
multigit_gx/src/mg_dialog_git_push_tag.py
multigit_gx/src/mg_dialog_git_revert.py
multigit_gx/src/mg_dialog_git_run_cmd.py
multigit_gx/src/mg_dialog_git_switch_delete_branch.py
multigit_gx/src/mg_dialog_git_tag.py
multigit_gx/src/mg_dialog_select_repo.py
multigit_gx/src/mg_dialog_settings.py
multigit_gx/src/mg_dialog_utils.py
multigit_gx/src/mg_dialog_view_properties.py
multigit_gx/src/mg_dialog_whatisnew.py
multigit_gx/src/mg_ensure_info_available.py
multigit_gx/src/mg_exec_task_item.py
multigit_gx/src/mg_exec_window.py
multigit_gx/src/mg_json_mgit_parser.py
multigit_gx/src/mg_multigit_widget.py
multigit_gx/src/mg_plugin_mgr.py
multigit_gx/src/mg_repo_info.py
multigit_gx/src/mg_repo_tree.py
multigit_gx/src/mg_repo_tree_item.py
multigit_gx/src/mg_tools.py
multigit_gx/src/mg_utils.py
multigit_gx/src/mg_window.py
multigit_gx/src/multigit_resources_rc.py
multigit_gx/src/gui/__init__.py
multigit_gx/src/gui/content_full_license_info.py
multigit_gx/src/gui/content_whatisnew.py
multigit_gx/src/gui/gen_and_patch_ui.py
multigit_gx/src/gui/ui_about.py
multigit_gx/src/gui/ui_about_license.py
multigit_gx/src/gui/ui_apply_mgit_file.py
multigit_gx/src/gui/ui_clone_from_mgit.py
multigit_gx/src/gui/ui_export_csv.py
multigit_gx/src/gui/ui_export_mgit.py
multigit_gx/src/gui/ui_git_commit.py
multigit_gx/src/gui/ui_git_create_branch.py
multigit_gx/src/gui/ui_git_delete_branch.py
multigit_gx-1.7.1.dist-info/METADATA
multigit_gx-1.7.1.dist-info/WHEEL
multigit_gx-1.7.1.dist-info/entry_points.txt
multigit_gx-1.7.1.dist-info/licenses/FULL_LICENSING_INFORMATION.md
multigit_gx-1.7.1.dist-info/licenses/LICENSE.txt
multigit_gx-1.7.1.dist-info/RECORD
