Metadata-Version: 2.4
Name: multigit-gx
Version: 1.7.1
Summary: Multigit is a graphical tool designed to simplify working with projects composed of multiple git repositories.
Project-URL: Documentation, https://github.com/idemia/multigit#readme
Project-URL: Issues, https://github.com/idemia/multigit/issues
Project-URL: Source, https://github.com/idemia/multigit
Author-email: Philippe Fremy <philippe.fremy@idemia.com>
License-Expression: Apache-2.0
License-File: FULL_LICENSING_INFORMATION.md
License-File: LICENSE.txt
Keywords: frontend,git
Classifier: Development Status :: 5 - Production/Stable
Classifier: Environment :: Win32 (MS Windows)
Classifier: Environment :: X11 Applications :: Qt
Classifier: Intended Audience :: Developers
Classifier: Topic :: Software Development :: User Interfaces
Classifier: Topic :: Software Development :: Version Control :: Git
Requires-Python: >=3.8
Requires-Dist: concurrent-log-handler
Requires-Dist: pyside6
Provides-Extra: dev
Requires-Dist: jsonschema-cli; extra == 'dev'
Requires-Dist: markdown2; extra == 'dev'
Requires-Dist: mypy; extra == 'dev'
Requires-Dist: pyinstaller; (platform_system == 'Windows') and extra == 'dev'
Requires-Dist: pyside6-stubs; extra == 'dev'
Requires-Dist: pytest<8; extra == 'dev'
Requires-Dist: pyyaml==5.3.1; extra == 'dev'
